plasmidplots/__init__.py
plasmidplots/ncbi_tools.py
plasmidplots/pplots.py
plasmidplots/utilities.py
plasmidplots-1.6.3.dist-info/LICENSE
plasmidplots-1.6.3.dist-info/METADATA
plasmidplots-1.6.3.dist-info/WHEEL
plasmidplots-1.6.3.dist-info/top_level.txt
plasmidplots-1.6.3.dist-info/RECORD
