Metadata-Version: 2.1
Name: plasmidplots
Version: 1.6.3
Summary: Library for plotting gene matches on plasmids
Home-page: https://github.com/Chenkail/plasmidplots
Author: Chenkai Luo
Author-email: chenkai.luo@gmail.com
License: UNKNOWN
Platform: UNKNOWN
Classifier: Programming Language :: Python :: 3
Classifier: License :: OSI Approved :: GNU General Public License v3 (GPLv3)
Classifier: Operating System :: OS Independent
